TPRAM.v
// implementation of two-port-ram(Fake)

module TPRAM (
    input clk,

    input wea,                  //enable write signal of channel a
    input enb,                  //enable signal of channel b

    input [7:0] addra,          //address of channel a
    input [7:0] addrb,          //address of channle b

    input [15:0] data_i_a,      //data input of channel a
    output reg [15:0] data_o_b //data output of channel b
);
reg [15:0] RAM [255:0];         //DATAWIDTH = 16, DEPTH = 256 = 2^8

always @(posedge clk) begin     //write channel
    if(wea) begin
        RAM[addra] <= data_i_a;
    end
end

always @(posedge clk) begin    //read channel
    if(enb) begin
        data_o_b <= RAM[addrb];
    end
end
endmodule

testbench_TPRAM.v
`timescale 1ns/100ps
`include "TPRAM.v"
module real_dual_port_ram_tb ();
reg          clk,wea,enb                    ; 
reg   [7:0]  addra,addrb                    ;
reg   [15:0] data_i_a                       ;
wire   [15:0] data_o_b                       ;

always #5 clk = ~clk;
// instantiation
TPRAM inst_TPRAM(
    .clk(clk),
    .wea(wea),
    .enb(enb),
    .addra(addra),
    .addrb(addrb),
    .data_i_a(data_i_a),
    .data_o_b(data_o_b)
);
initial begin
    clk <= 0;
    #25
    wea<=1;enb<=1;addra<=8'd0;addrb<=8'd0;data_i_a<=16'd9;
    #20
    wea<=1;enb<=1;addra<=8'd1;addrb<=8'd1;data_i_a<=16'd2;
    #20
    wea<=1;enb<=1;addra<=8'd2;addrb<=8'd2;data_i_a<=16'd7;
    #20
    wea<=1;enb<=1;addra<=8'd3;addrb<=8'd3;data_i_a<=16'd7;
end

/*iverilog */
initial begin
    $dumpfile("waveform_TPRAM.vcd");//generate waveform file
    $dumpvars;//or $dumpvars;
    #200 //simulation time
    $finish;
end
/*iverilog */

endmodule

waveform_TPRAM.vcd
$date
	Wed Jan 11 00:39:44 2023
$end
$version
	Icarus Verilog
$end
$timescale
	100ps
$end
$scope module real_dual_port_ram_tb $end
$var wire 16 ! data_o_b [15:0] $end
$var reg 8 " addra [7:0] $end
$var reg 8 # addrb [7:0] $end
$var reg 1 $ clk $end
$var reg 16 % data_i_a [15:0] $end
$var reg 1 & enb $end
$var reg 1 ' wea $end
$scope module inst_TPRAM $end
$var wire 8 ( addra [7:0] $end
$var wire 8 ) addrb [7:0] $end
$var wire 1 $ clk $end
$var wire 16 * data_i_a [15:0] $end
$var wire 1 & enb $end
$var wire 1 ' wea $end
$var reg 16 + data_o_b [15:0] $end
$upscope $end
$upscope $end
$enddefinitions $end
#0
$dumpvars
bx +
bx *
bx )
bx (
x'
x&
bx %
0$
bx #
bx "
bx !
$end
#50
1$
#100
0$
#150
1$
#200
0$
#250
b1001 %
b1001 *
b0 #
b0 )
b0 "
b0 (
1&
1'
1$
#300
0$
#350
1$
#400
0$
#450
b1001 !
b1001 +
b10 %
b10 *
b1 #
b1 )
b1 "
b1 (
1$
#500
0$
#550
bx !
bx +
1$
#600
0$
#650
b10 !
b10 +
b111 %
b111 *
b10 #
b10 )
b10 "
b10 (
1$
#700
0$
#750
bx !
bx +
1$
#800
0$
#850
b111 !
b111 +
b11 #
b11 )
b11 "
b11 (
1$
#900
0$
#950
bx !
bx +
1$
#1000
0$
#1050
b111 !
b111 +
1$
