DPRAM.v
// implementation of dual-port-ram(Real)

module DPRAM (
    input clka,
    input clkb,

    input ena,                  //enable signal of channel a
    input enb,                  //enable signal of channel b

    input wea,                  //enable write signal of channel a
    input web,                  //enable write signal of channel b

    input [7:0] addra,          //address of channel a
    input [7:0] addrb,          //address of channle b

    input [15:0] data_i_a,      //data input of channel a
    input [15:0] data_i_b,      //data input of channel b

    output reg [15:0] data_o_a, //data output of channel a
    output reg [15:0] data_o_b //data output of channel b
);
reg [15:0] RAM [255:0];         //DATAWIDTH = 16, DEPTH = 256 = 2^8

always @(posedge clka) begin     
    if(ena) begin
        if(wea) begin
            RAM[addra] <= data_i_a;
        end
        data_o_a <= RAM[addra];
    end
end

always @(posedge clkb) begin     
    if(enb) begin
        if(wea) begin
            RAM[addrb] <= data_i_b;
        end
        data_o_b <= RAM[addrb];
    end
end
endmodule

testbench_DPRAM.v
`timescale 1ns/100ps
`include "DPRAM.v"
module real_dual_port_ram_tb ();
reg          clka,clkb,ena,enb,wea,web     ; 
reg   [7:0]  addra,addrb                   ;
reg   [15:0] data_i_a,data_i_b             ;
wire   [15:0] data_o_a,data_o_b             ;

always #5 clka = ~clka;
always #5 clkb = ~clkb;
// instantiation
DPRAM inst_DPRAM(
    .clka(clka),
    .clkb(clkb),
    .ena(ena),
    .enb(enb),
    .wea(wea),
    .web(web),
    .addra(addra),
    .addrb(addrb),
    .data_i_a(data_i_a),
    .data_i_b(data_i_b),
    .data_o_a(data_o_a),
    .data_o_b(data_o_b)
);
initial begin
    clka <= 0;
    clkb <= 0;
    #25
    ena<=1;enb<=1;wea<=1;web<=1;addra<=8'd0;addrb<=8'd1;data_i_a<=16'd9;data_i_b<=16'd10;
    #20
    ena<=1;enb<=1;wea<=1;web<=1;addra<=8'd2;addrb<=8'd3;data_i_a<=16'd7;data_i_b<=16'd7;
    #20
    ena<=1;enb<=1;wea<=1;web<=1;addra<=8'd4;addrb<=8'd5;data_i_a<=16'd6;data_i_b<=16'd8;
    #20
    ena<=1;enb<=1;wea<=1;web<=1;addra<=8'd2;addrb<=8'd3;data_i_a<=16'd0;data_i_b<=16'd0;
end

/*iverilog */
initial begin
    $dumpfile("waveform_DPRAM.vcd");//generate waveform file
    $dumpvars;//or $dumpvars;
    #200 //simulation time
    $finish;
end
/*iverilog */

endmodule

waveform_DPRAM.vcd
$date
	Wed Jan 11 00:48:46 2023
$end
$version
	Icarus Verilog
$end
$timescale
	100ps
$end
$scope module real_dual_port_ram_tb $end
$var wire 16 ! data_o_b [15:0] $end
$var wire 16 " data_o_a [15:0] $end
$var reg 8 # addra [7:0] $end
$var reg 8 $ addrb [7:0] $end
$var reg 1 % clka $end
$var reg 1 & clkb $end
$var reg 16 ' data_i_a [15:0] $end
$var reg 16 ( data_i_b [15:0] $end
$var reg 1 ) ena $end
$var reg 1 * enb $end
$var reg 1 + wea $end
$var reg 1 , web $end
$scope module inst_DPRAM $end
$var wire 8 - addra [7:0] $end
$var wire 8 . addrb [7:0] $end
$var wire 1 % clka $end
$var wire 1 & clkb $end
$var wire 16 / data_i_a [15:0] $end
$var wire 16 0 data_i_b [15:0] $end
$var wire 1 ) ena $end
$var wire 1 * enb $end
$var wire 1 + wea $end
$var wire 1 , web $end
$var reg 16 1 data_o_a [15:0] $end
$var reg 16 2 data_o_b [15:0] $end
$upscope $end
$upscope $end
$enddefinitions $end
#0
$dumpvars
bx 2
bx 1
bx 0
bx /
bx .
bx -
x,
x+
x*
x)
bx (
bx '
0&
0%
bx $
bx #
bx "
bx !
$end
#50
1&
1%
#100
0&
0%
#150
1&
1%
#200
0&
0%
#250
b1010 (
b1010 0
b1001 '
b1001 /
b1 $
b1 .
b0 #
b0 -
1,
1+
1*
1)
1&
1%
#300
0&
0%
#350
1&
1%
#400
0&
0%
#450
b1010 !
b1010 2
b1001 "
b1001 1
b111 (
b111 0
b111 '
b111 /
b11 $
b11 .
b10 #
b10 -
1&
1%
#500
0&
0%
#550
bx !
bx 2
bx "
bx 1
1&
1%
#600
0&
0%
#650
b111 !
b111 2
b111 "
b111 1
b1000 (
b1000 0
b110 '
b110 /
b101 $
b101 .
b100 #
b100 -
1&
1%
#700
0&
0%
#750
bx !
bx 2
bx "
bx 1
1&
1%
#800
0&
0%
#850
b1000 !
b1000 2
b110 "
b110 1
b0 (
b0 0
b0 '
b0 /
b11 $
b11 .
b10 #
b10 -
1&
1%
#900
0&
0%
#950
b111 !
b111 2
b111 "
b111 1
1&
1%
#1000
0&
0%
#1050
b0 !
b0 2
b0 "
b0 1
1&
1%
